{
  "main": {
    "id": "24fce88462b3460c",
    "type": "split",
    "children": [
      {
        "id": "6e244f015164657b",
        "type": "tabs",
        "children": [
          {
            "id": "048eaf3aa1205802",
            "type": "leaf",
            "state": {
              "type": "markdown",
              "state": {
                "file": "Welcome.md",
                "mode": "source",
                "source": false
              },
              "icon": "lucide-file",
              "title": "Welcome"
            }
          },
          {
            "id": "603e98592ee338e1",
            "type": "leaf",
            "state": {
              "type": "markdown",
              "state": {
                "file": "Course Report.md",
                "mode": "source",
                "source": false
              },
              "icon": "lucide-file",
              "title": "Course Report"
            }
          }
        ],
        "currentTab": 1
      }
    ],
    "direction": "vertical"
  },
  "left": {
    "id": "6a979567b149d557",
    "type": "split",
    "children": [
      {
        "id": "d8d73cb0b474ee7d",
        "type": "tabs",
        "children": [
          {
            "id": "3653e7ef77cf0322",
            "type": "leaf",
            "state": {
              "type": "file-explorer",
              "state": {
                "sortOrder": "alphabetical",
                "autoReveal": false
              },
              "icon": "lucide-folder-closed",
              "title": "Files"
            }
          },
          {
            "id": "585a97b353a3b618",
            "type": "leaf",
            "state": {
              "type": "search",
              "state": {
                "query": "",
                "matchingCase": false,
                "explainSearch": false,
                "collapseAll": false,
                "extraContext": false,
                "sortOrder": "alphabetical"
              },
              "icon": "lucide-search",
              "title": "Search"
            }
          },
          {
            "id": "762ba060a6a1113f",
            "type": "leaf",
            "state": {
              "type": "bookmarks",
              "state": {},
              "icon": "lucide-bookmark",
              "title": "Bookmarks"
            }
          }
        ]
      }
    ],
    "direction": "horizontal",
    "width": 300
  },
  "right": {
    "id": "c21d3b0576a5bd26",
    "type": "split",
    "children": [
      {
        "id": "a7d81010c36e5a90",
        "type": "tabs",
        "children": [
          {
            "id": "083bbf73763160f1",
            "type": "leaf",
            "state": {
              "type": "backlink",
              "state": {
                "file": "Course Report.md",
                "collapseAll": false,
                "extraContext": false,
                "sortOrder": "alphabetical",
                "showSearch": false,
                "searchQuery": "",
                "backlinkCollapsed": false,
                "unlinkedCollapsed": true
              },
              "icon": "links-coming-in",
              "title": "Backlinks for Course Report"
            }
          },
          {
            "id": "aa0431691ec53931",
            "type": "leaf",
            "state": {
              "type": "outgoing-link",
              "state": {
                "file": "Course Report.md",
                "linksCollapsed": false,
                "unlinkedCollapsed": true
              },
              "icon": "links-going-out",
              "title": "Outgoing links from Course Report"
            }
          },
          {
            "id": "268e3f410a1c9f93",
            "type": "leaf",
            "state": {
              "type": "tag",
              "state": {
                "sortOrder": "frequency",
                "useHierarchy": true,
                "showSearch": false,
                "searchQuery": ""
              },
              "icon": "lucide-tags",
              "title": "Tags"
            }
          },
          {
            "id": "f48c0c40934a3a3e",
            "type": "leaf",
            "state": {
              "type": "all-properties",
              "state": {
                "sortOrder": "frequency",
                "showSearch": false,
                "searchQuery": ""
              },
              "icon": "lucide-archive",
              "title": "All properties"
            }
          },
          {
            "id": "6845dc60d0ec4df2",
            "type": "leaf",
            "state": {
              "type": "outline",
              "state": {
                "file": "Course Report.md",
                "followCursor": false,
                "showSearch": false,
                "searchQuery": ""
              },
              "icon": "lucide-list",
              "title": "Outline of Course Report"
            }
          }
        ]
      }
    ],
    "direction": "horizontal",
    "width": 300,
    "collapsed": true
  },
  "left-ribbon": {
    "hiddenItems": {
      "switcher:Open quick switcher": false,
      "graph:Open graph view": false,
      "canvas:Create new canvas": false,
      "daily-notes:Open today's daily note": false,
      "templates:Insert template": false,
      "command-palette:Open command palette": false,
      "bases:Create new base": false
    }
  },
  "active": "603e98592ee338e1",
  "lastOpenFiles": [
    "Report.md",
    "Course Report 1.md",
    "Course Report.md",
    "Welcome.md",
    "OOP"
  ]
}